[{"key":"setting10","value":92,"defaultValue":30,"enabled":false},{"key":"setting107","value":33,"defaultValue":47,"enabled":false},{"key":"setting111","value":95,"defaultValue":28,"enabled":true},{"key":"setting119","value":42,"defaultValue":42,"enabled":false},{"key":"setting129","value":32,"defaultValue":30,"enabled":true},{"key":"setting142","value":84,"defaultValue":27,"enabled":true},{"key":"setting145","value":3,"defaultValue":23,"enabled":false},{"key":"setting147","value":33,"defaultValue":21,"enabled":false},{"key":"setting151","value":76,"defaultValue":31,"enabled":false},{"key":"setting153","value":64,"defaultValue":22,"enabled":false},{"key":"setting154","value":85,"defaultValue":9,"enabled":false},{"key":"setting157","value":82,"defaultValue":33,"enabled":false},{"key":"setting170","value":3,"defaultValue":24,"enabled":true},{"key":"setting172","value":67,"defaultValue":7,"enabled":true},{"key":"setting173","value":44,"defaultValue":15,"enabled":true},{"key":"setting183","value":12,"defaultValue":29,"enabled":false},{"key":"setting185","value":64,"defaultValue":14,"enabled":false},{"key":"setting224","value":12,"defaultValue":41,"enabled":true},{"key":"setting242","value":8,"defaultValue":44,"enabled":false},{"key":"setting243","value":57,"defaultValue":14,"enabled":false},{"key":"setting245","value":85,"defaultValue":10,"enabled":false},{"key":"setting248","value":26,"defaultValue":36,"enabled":true},{"key":"setting250","value":54,"defaultValue":45,"enabled":true},{"key":"setting260","value":77,"defaultValue":24,"enabled":true},{"key":"setting266","value":5,"defaultValue":32,"enabled":false},{"key":"setting267","value":3,"defaultValue":43,"enabled":true},{"key":"setting27","value":85,"defaultValue":26,"enabled":false},{"key":"setting270","value":70,"defaultValue":30,"enabled":false},{"key":"setting272","value":57,"defaultValue":11,"enabled":true},{"key":"setting282","value":14,"defaultValue":33,"enabled":true},{"key":"setting288","value":18,"defaultValue":6,"enabled":false},{"key":"setting30","value":99,"defaultValue":17,"enabled":true},{"key":"setting300","value":17,"defaultValue":46,"enabled":true},{"key":"setting306","value":17,"defaultValue":13,"enabled":true},{"key":"setting312","value":23,"defaultValue":40,"enabled":true},{"key":"setting32","value":1,"defaultValue":14,"enabled":true},{"key":"setting326","value":15,"defaultValue":26,"enabled":true},{"key":"setting334","value":91,"defaultValue":3,"enabled":true},{"key":"setting337","value":75,"defaultValue":24,"enabled":false},{"key":"setting346","value":61,"defaultValue":28,"enabled":true},{"key":"setting350","value":98,"defaultValue":47,"enabled":false},{"key":"setting358","value":36,"defaultValue":3,"enabled":false},{"key":"setting360","value":56,"defaultValue":32,"enabled":false},{"key":"setting37","value":0,"defaultValue":7,"enabled":false},{"key":"setting381","value":73,"defaultValue":18,"enabled":true},{"key":"setting382","value":95,"defaultValue":41,"enabled":false},{"key":"setting383","value":99,"defaultValue":1,"enabled":false},{"key":"setting384","value":40,"defaultValue":39,"enabled":true},{"key":"setting387","value":13,"defaultValue":24,"enabled":true},{"key":"setting403","value":32,"defaultValue":2,"enabled":true},{"key":"setting408","value":90,"defaultValue":5,"enabled":false},{"key":"setting41","value":30,"defaultValue":12,"enabled":true},{"key":"setting443","value":68,"defaultValue":21,"enabled":true},{"key":"setting453","value":97,"defaultValue":11,"enabled":true},{"key":"setting458","value":55,"defaultValue":15,"enabled":true},{"key":"setting55","value":56,"defaultValue":47,"enabled":false},{"key":"setting58","value":6,"defaultValue":22,"enabled":true},{"key":"setting62","value":15,"defaultValue":44,"enabled":false},{"key":"setting63","value":1,"defaultValue":35,"enabled":true},{"key":"setting94","value":4,"defaultValue":47,"enabled":true}]